edapi/__init__.py
edapi/constants.py
edapi/edapi.py
edapi/utils.py
edapi/types/__init__.py
edapi/types/types.py
edapi/types/api_types/__init__.py
edapi/types/api_types/category.py
edapi/types/api_types/content.py
edapi/types/api_types/course.py
edapi/types/api_types/thread.py
edapi/types/api_types/user.py
edapi/types/api_types/endpoints/__init__.py
edapi/types/api_types/endpoints/activity.py
edapi/types/api_types/endpoints/files.py
edapi/types/api_types/endpoints/threads.py
edapi/types/api_types/endpoints/user.py
edapi-0.0.2.dist-info/LICENSE
edapi-0.0.2.dist-info/METADATA
edapi-0.0.2.dist-info/WHEEL
edapi-0.0.2.dist-info/top_level.txt
edapi-0.0.2.dist-info/RECORD
