Metadata-Version: 2.1
Name: edapi
Version: 0.0.2
Project-URL: Homepage, https://github.com/smartspot2/edapi
Classifier: License :: OSI Approved :: GNU General Public License v3 (GPLv3)
License-File: LICENSE
